README.txt
setup.py
lobomarinopython/__init__.py
lobomarinopython.egg-info/PKG-INFO
lobomarinopython.egg-info/SOURCES.txt
lobomarinopython.egg-info/dependency_links.txt
lobomarinopython.egg-info/top_level.txt